LICENSE
hardwario/common/__init__.py
hardwario/common/cli.py
hardwario/common/pib.py
hardwario/common/util.py
hardwario_common-1.9.0.dist-info/LICENSE
hardwario_common-1.9.0.dist-info/METADATA
hardwario_common-1.9.0.dist-info/WHEEL
hardwario_common-1.9.0.dist-info/entry_points.txt
hardwario_common-1.9.0.dist-info/RECORD
