Metadata-Version: 2.1
Name: hardwario-common
Version: 1.9.0
Summary: HARDWARIO Common
Home-page: https://github.com/hardwario/py-hardwario-common
License: MIT
Author: Karel Blavka
Author-email: karel.blavka@hardwario.com
Requires-Python: >=3.8
Classifier: Development Status :: 5 - Production/Stable
Classifier: Environment :: Console
Classifier: License :: OSI Approved :: MIT License
Classifier: Operating System :: OS Independent
Classifier: Programming Language :: Python :: 3
Classifier: Programming Language :: Python :: 3.8
Classifier: Programming Language :: Python :: 3.9
Classifier: Programming Language :: Python :: 3.10
Classifier: Programming Language :: Python :: 3.11
Classifier: Programming Language :: Python :: 3.12
Classifier: Programming Language :: Python :: 3.7
Classifier: Topic :: Software Development :: Libraries :: Python Modules
Classifier: Topic :: Utilities
Requires-Dist: click (>=8.1.7,<9.0.0)
Requires-Dist: loguru (>=0.7.2,<0.8.0)
Requires-Dist: pycodestyle (>=2.11.1,<3.0.0)
Project-URL: Repository, https://github.com/hardwario/py-hardwario-common
